Workbook

Sheet Menu
A1: Sourcing Analysis with AI

Sheet Executive Summary
A1: Executive Summary
B5: Total candidates | E5: Overall hiring rate | H5: Largest Bottleneck
B6: =GETPIVOTDATA("candidate_id",tables!$A$1) -> 601 | E6: =tables!K10 -> 0.081530782 | H6: =Analysis!C16 -> 0.30845771
B9: Across 4 roles | E9: 49 hires | H9: Teste taken > offer
B12: Best Source | E12: Top Recruiter Rate | H12: Reject Reason
B13: =Analysis!C62 -> Github | E13: =Analysis!E80 -> 0.15306122 | H13: =Analysis!E131 -> No response
B16: 11% hiring rate | E16: Bruno | H16: 210 candidates
A19: Key Insights

Sheet Analysis
A1: Analysis
A4: Funnel
A9: Overall
A10: Stage | B10: Candidates | C10: Conversion
A11: Sourced | B11: 601
A12: Response | B12: 408 | C12: =B12/B11 -> 0.67886855
A13: Screening Pass | B13: 308 | C13: =B13/B12 -> 0.75490196
A14: Interview Pass | B14: 234 | C14: =B14/B13 -> 0.75974026
A15: Test Taken | B15: 201 | C15: =B15/B14 -> 0.85897436
A16: Offer | B16: 62 | C16: =B16/B15 -> 0.30845771
A17: Hired | B17: 49 | C17: =B17/B16 -> 0.79032258
A22: Key Insight
A23: Only 31% of candidates who take the technical test receive an offer. This is the largest drop in the overall funnel and should trigger a review of assessment calibration, pre-test qualification, and final decision criteria.
A26: Funnel by role
A27: Analista de Dados | E27: Analista de Recrutamento
A28: Stage | B28: Candidates | C28: Conversion | E28: Stage | F28: Candidates | G28: Conversion
A29: Sourced | B29: 162 | E29: Sourced | F29: 147
A30: Response | B30: 118 | C30: =B30/B29 -> 0.72839506 | E30: Response | F30: 106 | G30: =F30/F29 -> 0.72108844
A31: Screening Pass | B31: 94 | C31: =B31/B30 -> 0.79661017 | E31: Screening Pass | F31: 82 | G31: =F31/F30 -> 0.77358491
A32: Interview Pass | B32: 70 | C32: =B32/B31 -> 0.74468085 | E32: Interview Pass | F32: 62 | G32: =F32/F31 -> 0.75609756
A33: Test Taken | B33: 63 | C33: =B33/B32 -> 0.9 | E33: Test Taken | F33: 49 | G33: =F33/F32 -> 0.79032258
A34: Offer | B34: 15 | C34: =B34/B33 -> 0.23809524 | E34: Offer | F34: 19 | G34: =F34/F33 -> 0.3877551
A35: Hired | B35: 11 | C35: =B35/B34 -> 0.73333333 | E35: Hired | F35: 17 | G35: =F35/F34 -> 0.89473684
A37: People BP | E37: Talent Acquisition Specialist
A38: Stage | B38: Candidates | C38: Conversion | E38: Stage | F38: Candidates | G38: Conversion
A39: Sourced | B39: 165 | E39: Sourced | F39: 127
A40: Response | B40: 105 | C40: =B40/B39 -> 0.63636364 | E40: Response | F40: 79 | G40: =F40/F39 -> 0.62204724
A41: Screening Pass | B41: 77 | C41: =B41/B40 -> 0.73333333 | E41: Screening Pass | F41: 55 | G41: =F41/F40 -> 0.69620253
A42: Interview Pass | B42: 59 | C42: =B42/B41 -> 0.76623377 | E42: Interview Pass | F42: 43 | G42: =F42/F41 -> 0.78181818
A43: Test Taken | B43: 49 | C43: =B43/B42 -> 0.83050847 | E43: Test Taken | F43: 40 | G43: =F43/F42 -> 0.93023256
A44: Offer | B44: 17 | C44: =B44/B43 -> 0.34693878 | E44: Offer | F44: 11 | G44: =F44/F43 -> 0.275
A45: Hired | B45: 14 | C45: =B45/B44 -> 0.82352941 | E45: Hired | F45: 7 | G45: =F45/F44 -> 0.63636364
A47: Role-Level Interpretation
A48: The Test → Offer stage is the main bottleneck for every role. Data Analyst has the lowest conversion at this point (23.8%), while Recruitment Analyst has the highest (38.8%). Talent Acquisition Specialist and People BP also show lower response rates at the top of the funnel, suggesting an additional opportunity to review candidate approach and role positioning.
A51: Source Channels
A52: Channel | B52: Hired NO | C52: Hired YES | D52: Total Geral | E52: Channel representative | F52: Channel hire conversation
C54: Channel | D54: No hired | E54: Hired | F54: Total | G54: Channel Representative | H54: Hire conversation
C55: Indicação | D55: 61 | E55: 3 | F55: 64 | G55: =F55/$F$63 -> 0.10648918 | H55: =E55/F55 -> 0.046875
C56: Evento | D56: 78 | E56: 4 | F56: 82 | G56: =F56/$F$63 -> 0.13643927 | H56: =E56/F56 -> 0.048780488
C57: Banco de Talentos | D57: 62 | E57: 6 | F57: 68 | G57: =F57/$F$63 -> 0.11314476 | H57: =E57/F57 -> 0.088235294
C58: Hunting | D58: 68 | E58: 7 | F58: 75 | G58: =F58/$F$63 -> 0.12479201 | H58: =E58/F58 -> 0.093333333
C59: Inbound | D59: 62 | E59: 7 | F59: 69 | G59: =F59/$F$63 -> 0.11480865 | H59: =E59/F59 -> 0.10144928
C60: LinkedIn | D60: 74 | E60: 7 | F60: 81 | G60: =F60/$F$63 -> 0.13477537 | H60: =E60/F60 -> 0.086419753
C61: Comunidade | D61: 82 | E61: 7 | F61: 89 | G61: =F61/$F$63 -> 0.14808652 | H61: =E61/F61 -> 0.078651685
C62: Github | D62: 65 | E62: 8 | F62: 73 | G62: =F62/$F$63 -> 0.12146423 | H62: =E62/F62 -> 0.10958904
C63: Total Geral | D63: 552 | E63: 49 | F63: 601
A65: Key Insights
A66: GitHub and Inbound show the highest hire conversion rates in the dataset, suggesting that recruiters may benefit from prioritizing these channels when building pipelines. However, volume and role mix should be considered before reallocating effort.
A68: Investigate: Referral and Event sourcing show the lowest overall conversion. Referral should remain part of the strategy because it is often passive and low-effort. Event sourcing deserves a cost-benefit review, especially if it requires significant budget and operational effort.
A71: Recruiter Performance
A74: Recruiter | B74: Hired NO | C74: Hired YES | D74: Candidates | E74: Hired YES Conversation
A75: Fernanda | B75: 99 | C75: 4 | D75: 103 | E75: =C75/D75 -> 0.038834951
A76: Diego | B76: 98 | C76: 5 | D76: 103 | E76: =C76/D76 -> 0.048543689
A77: Gustavo | B77: 115 | C77: 6 | D77: 121 | E77: =C77/D77 -> 0.049586777
A78: Carla | B78: 92 | C78: 9 | D78: 101 | E78: =C78/D78 -> 0.089108911
A79: Ana | B79: 65 | C79: 10 | D79: 75 | E79: =C79/D79 -> 0.13333333
A80: Bruno | B80: 83 | C80: 15 | D80: 98 | E80: =C80/D80 -> 0.15306122
A81: Total Geral | B81: 552 | C81: 49 | D81: 601
A83: Key Insights
A84: Interpretation with caution: Gustavo managed the largest pipeline but achieved one of the lowest hire conversion rates. This should not be interpreted as individual underperformance without understanding role complexity, seniority, sourcing channels, and requisition difficulty.
A86: Learning opportunity: Bruno and Ana handled smaller pipelines while achieving the highest conversion rates. Their sourcing and qualification practices could be reviewed and shared with the team, while controlling for portfolio differences.
A89: Candidates Signals
A92: Response time | B92: Hire Rate
A93: 2–3 days | B93: 0.078 | D93: Key Insight
A94: 8–10 days | B94: 0.093 | D94: When to persist: Candidates with the highest hire rates were not necessarily those who responded fastest. Response time alone should not be used as a stop signal. Recruiters should continue follow-up when other indicators suggest potential.
A95: 11+ days | B95: 0.115
A96: 0–1 day | B96: 0.138
A97: 4–5 days | B97: 0.138
A98: 6–7 days | B98: 0.149
A103: Signal | B103: Not Hired | C103: Hired
A104: Years Experience | B104: 5.5 | C104: 6.5
A105: Behavior Score | B105: 74 | C105: 80.1
A106: Manager Score | B106: 73.1 | C106: 80.9
A107: Technical Score | B107: 72.9 | C107: 82.4
A114: Key Insight
A115: Hiring pattern: Hired candidates tend to have more experience and higher assessment scores. On average, they have 6.5 years of experience and scores above 80 in technical, behavioral, and manager evaluations. These are associated patterns, not proof of causality.
A118: Rejections
E121: Reject Reason | F121: Candidates | G121: %
E122: Culture add mismatch | F122: 12 | G122: =F122/$F$132 -> 0.02173913
E123: Accepted another offer | F123: 18 | G123: =F123/$F$132 -> 0.032608696
E124: Salary mismatch | F124: 18 | G124: =F124/$F$132 -> 0.032608696
E125: Headcount closed | F125: 22 | G125: =F125/$F$132 -> 0.039855072
E126: Low engagement | F126: 23 | G126: =F126/$F$132 -> 0.041666667
E127: Low technical fit | F127: 23 | G127: =F127/$F$132 -> 0.041666667
E128: Timing mismatch | F128: 24 | G128: =F128/$F$132 -> 0.043478261
E129: Failed technical test | F129: 25 | G129: =F129/$F$132 -> 0.045289855
E130: (vazio) | F130: 177 | G130: =F130/$F$132 -> 0.32065217
E131: No response | F131: 210 | G131: =F131/$F$132 -> 0.38043478
E132: Total Geral | F132: =SUM(F122:F131) -> 552
A134: Key Insights
A135: Candidate engagement: No response is the most frequently documented rejection reason. This creates an opportunity to review outreach quality, follow-up cadence, value proposition, and candidate nurturing throughout the process.
A137: Data governance: 177 non-hired candidates have no rejection reason recorded. This limits the reliability of loss analysis and reduces the team's ability to identify recurring process issues.
A139: Recommendation: Standardize rejection reason completion in the ATS, clarify definitions, and monitor missing data as an operational KPI. Better data quality will enable more accurate diagnosis and safer use of AI in recruiting decisions.

Sheet Recommendations
A1: Recomendations
A25: Conclusion

Sheet rawdata
A1: Recomendations
A4: candidate_id | B4: candidate_name | C4: candidate_email | D4: requisition_id | E4: role | F4: department | G4: location | H4: work_mode | I4: seniority | J4: years_experience | K4: hiring_manager | L4: recruiter | M4: source_channel | N4: decision_source | O4: sourced_date | P4: first_contact_date | Q4: response_received | R4: response_time_days | S4: screening_pass | T4: screening_date | U4: interview1_pass | V4: interview1_date | W4: test_taken | X4: test_date | Y4: technical_test_score | Z4: behavior_score | AA4: manager_score | AB4: offer_sent | AC4: offer_date | AD4: hired | AE4: hired_date | AF4: final_stage | AG4: rejection_reason | AH4: stage_duration_days | AI4: recruiter_notes
A5: 1 | B5: Sr. Erick da Mota | C5: bruna89@da.org | D5: REQ-1037 | E5: Analista de Recrutamento | F5: Tech | G5: Campinas | H5: Presencial | I5: Senior | J5: 5.6 | K5: Luiz Fernando | L5: Carla | M5: Hunting | N5: Hiring Manager | O5: 45718 | P5: 45722 | Q5: TRUE | R5: 10 | S5: TRUE | T5: 45729 | U5: TRUE | V5: 45733 | W5: TRUE | X5: 45739 | Y5: 83 | Z5: 66 | AA5: 75 | AB5: FALSE | AD5: FALSE | AF5: Test | AH5: 21 | AI5: Experiência sólida, mas expectativa salarial alta.
A6: 2 | B6: Camila da Mota | C6: rafaelmartins@gmail.com | D6: REQ-1025 | E6: Talent Acquisition Specialist | F6: Tech | G6: Campinas | H6: Presencial | I6: Pleno | J6: 3.6 | K6: Benício | L6: Ana | M6: Comunidade | N6: Hiring Manager | O6: 45801 | P6: 45806 | Q6: TRUE | R6: 1 | S6: FALSE | U6: FALSE | W6: FALSE | Y6: 62 | Z6: 89 | AA6: 75 | AB6: FALSE | AD6: FALSE | AF6: Sourced | AH6: 5 | AI6: Perfil técnico acima da média.
A7: 3 | B7: Stephany Ferreira | C7: levida-mota@gmail.com | D7: REQ-1015 | E7: Analista de Dados | F7: People | G7: Rio de Janeiro | H7: Remoto | I7: Pleno | J7: 3.4 | K7: Davi | L7: Fernanda | M7: Banco de Talentos | N7: Hiring Manager | O7: 45761 | P7: 45765 | Q7: TRUE | R7: 9 | S7: TRUE | T7: 45766 | U7: TRUE | V7: 45779 | W7: TRUE | X7: 45785 | Y7: 73 | Z7: 55 | AA7: 48 | AB7: FALSE | AD7: FALSE | AF7: Test | AG7: No response | AH7: 24 | AI7: Bom potencial de evolução.
A8: 4 | B8: Samuel Pires | C8: da-rosapietra@carvalho.com | D8: REQ-1038 | E8: Analista de Dados | F8: Data | G8: Remote | H8: Presencial | I8: Senior | J8: 9.9 | K8: Davi Lucca | L8: Carla | M8: Banco de Talentos | N8: Hiring Manager | O8: 45793 | P8: 45799 | Q8: FALSE | S8: FALSE | U8: FALSE | W8: FALSE | Y8: 91 | Z8: 91 | AA8: 84 | AB8: FALSE | AD8: FALSE | AF8: Rejected | AG8: No response | AH8: 6 | AI8: Pediu prazo adicional para retorno.
A9: 5 | B9: Ana Júlia Teixeira | C9: ana-luiza81@souza.com | D9: REQ-1085 | E9: Analista de Recrutamento | F9: People | G9: Remote | H9: Presencial | I9: Junior | J9: 2.5 | K9: Isabelly | L9: Ana | M9: Banco de Talentos | N9: Recruiter | O9: 45757 | P9: 45758 | Q9: FALSE | S9: FALSE | U9: FALSE | W9: FALSE | Y9: 89 | Z9: 81 | AA9: 84 | AB9: FALSE | AD9: FALSE | AF9: Rejected | AG9: No response | AH9: 1 | AI9: Perfil técnico acima da média.
A10: 6 | B10: Sophia Souza | C10: isabellaribeiro@cunha.br | D10: REQ-1073 | E10: Analista de Dados | F10: People | G10: Campinas | H10: Híbrido | I10: Senior | J10: 8.5 | K10: Sophia | L10: Bruno | M10: Indicação | N10: Tech Panel | O10: 45764 | P10: 45764 | Q10: FALSE | S10: FALSE | U10: FALSE | W10: FALSE | Y10: 81 | Z10: 88 | AA10: 91 | AB10: FALSE | AD10: FALSE | AF10: Rejected | AG10: No response | AH10: 0 | AI10: Feedback positivo do gestor.
A11: 7 | B11: Benjamin Sales | C11: sabrina61@santos.br | D11: REQ-1002 | E11: Analista de Recrutamento | F11: People | G11: Curitiba | H11: Presencial | I11: Pleno | J11: 4.5 | K11: Antônio | L11: Carla | M11: Banco de Talentos | N11: Tech Panel | O11: 45685 | P11: 45686 | Q11: TRUE | R11: 10 | S11: TRUE | T11: 45693 | U11: TRUE | V11: 45698 | W11: TRUE | X11: 45705 | Y11: 69 | Z11: 65 | AA11: 73 | AB11: FALSE | AD11: FALSE | AF11: Test | AH11: 20 | AI11: Feedback positivo do gestor.
A12: 8 | B12: Lorena Castro | C12: emanuelly10@moraes.br | D12: REQ-1087 | E12: People BP | F12: Tech | G12: Rio de Janeiro | H12: Remoto | I12: Staff | J12: 9.2 | K12: Carlos Eduardo | L12: Ana | M12: Hunting | N12: Hiring Manager | O12: 45780 | P12: 45789 | Q12: TRUE | R12: 6 | S12: TRUE | T12: 45794 | U12: TRUE | V12: 45797 | W12: FALSE | Y12: 77 | Z12: 68 | AA12: 81 | AB12: FALSE | AD12: FALSE | AF12: Interview | AH12: 17 | AI12: Feedback positivo do gestor.
A13: 9 | B13: Benício Rocha | C13: alveslucca@rezende.br | D13: REQ-1079 | E13: People BP | F13: People | G13: Campinas | H13: Remoto | I13: Senior | J13: 5.4 | K13: Isabelly | L13: Bruno | M13: Indicação | N13: Hiring Manager | O13: 45672 | P13: 45672 | Q13: TRUE | R13: 11 | S13: FALSE | U13: FALSE | W13: FALSE | Y13: 94 | Z13: 87 | AA13: 100 | AB13: FALSE | AD13: FALSE | AF13: Sourced | AH13: 0 | AI13: Experiência sólida, mas expectativa salarial alta.
A14: 10 | B14: Daniel Duarte | C14: sophiacarvalho@hotmail.com | D14: REQ-1079 | E14: Analista de Dados | F14: Operations | G14: São Paulo | H14: Remoto | I14: Pleno | J14: 6.4 | K14: Bruna | L14: Gustavo | M14: Evento | N14: TA Lead | O14: 45659 | P14: 45665 | Q14: TRUE | R14: 6 | S14: FALSE | U14: FALSE | W14: FALSE | Y14: 77 | Z14: 54 | AA14: 61 | AB14: FALSE | AD14: FALSE | AF14: Sourced | AG14: Salary mismatch | AH14: 6 | AI14: Boa comunicação e resposta rápida.
A15: 11 | B15: Antônio Barros | C15: fpeixoto@cavalcanti.br | D15: REQ-1069 | E15: People BP | F15: Operations | G15: Remote | H15: Presencial | I15: Senior | J15: 8 | K15: Isaac | L15: Bruno | M15: LinkedIn | N15: TA Lead | O15: 45669 | P15: 45672 | Q15: TRUE | R15: 11 | S15: TRUE | T15: 45680 | U15: TRUE | V15: 45691 | W15: TRUE | X15: 45698 | Y15: 61 | Z15: 78 | AA15: 71 | AB15: FALSE | AD15: FALSE | AF15: Test | AG15: Failed technical test | AH15: 29 | AI15: Pediu prazo adicional para retorno.
A16: 12 | B16: Evelyn Viana | C16: ana-vitoria30@bol.com.br | D16: REQ-1082 | E16: Talent Acquisition Specialist | F16: People | G16: Campinas | H16: Remoto | I16: Senior | J16: 6.2 | K16: Laís | L16: Gustavo | M16: Inbound | N16: Recruiter | O16: 45736 | P16: 45736 | Q16: FALSE | S16: FALSE | U16: FALSE | W16: FALSE | Y16: 67 | Z16: 66 | AA16: 70 | AB16: FALSE | AD16: FALSE | AF16: Rejected | AG16: No response | AH16: 0 | AI16: Experiência sólida, mas expectativa salarial alta.
A17: 13 | B17: Arthur Aragão | C17: carvalhomarcela@silva.com | D17: REQ-1067 | E17: Analista de Recrutamento | F17: Tech | G17: Rio de Janeiro | H17: Híbrido | I17: Senior | J17: 8.7 | K17: Carolina | L17: Carla | M17: Hunting | N17: Tech Panel | O17: 45784 | P17: 45787 | Q17: TRUE | R17: 1 | S17: TRUE | T17: 45794 | U17: TRUE | V17: 45808 | W17: TRUE | X17: 45810 | Y17: 76 | Z17: 78 | AA17: 74 | AB17: TRUE | AC17: 45816 | AD17: TRUE | AE17: 45824 | AF17: Hired | AH17: 40 | AI17: Pontos fortes em execução e autonomia.
A18: 14 | B18: Bárbara Cavalcanti | C18: ana78@ig.com.br | D18: REQ-1054 | E18: Talent Acquisition Specialist | F18: Tech | G18: Belo Horizonte | H18: Remoto | I18: Pleno | J18: 6 | K18: Stella | L18: Diego | M18: Banco de Talentos | N18: Hiring Manager | O18: 45724 | P18: 45729 | Q18: FALSE | S18: FALSE | U18: FALSE | W18: FALSE | Y18: 77 | Z18: 54 | AA18: 70 | AB18: FALSE | AD18: FALSE | AF18: Rejected | AG18: No response | AH18: 5 | AI18: Pediu prazo adicional para retorno.
A19: 15 | B19: Caroline Pereira | C19: davi85@yahoo.com.br | D19: REQ-1014 | E19: Talent Acquisition Specialist | F19: Operations | G19: Rio de Janeiro | H19: Remoto | I19: Senior | J19: 7 | K19: Sofia | L19: Fernanda | M19: Github | N19: Tech Panel | O19: 45772 | P19: 45775 | Q19: FALSE | S19: FALSE | U19: FALSE | W19: FALSE | Y19: 78 | Z19: 79 | AA19: 72 | AB19: FALSE | AD19: FALSE | AF19: Rejected | AG19: No response | AH19: 3 | AI19: Perfil técnico acima da média.
A20: 16 | B20: João Lucas Rocha | C20: yfernandes@ig.com.br | D20: REQ-1012 | E20: People BP | F20: Data | G20: Remote | H20: Remoto | I20: Junior | J20: 1.2 | K20: João Pedro | L20: Bruno | M20: Indicação | N20: Hiring Manager | O20: 45788 | P20: 45788 | Q20: TRUE | R20: 9 | S20: TRUE | T20: 45790 | U20: FALSE | W20: FALSE | Y20: 66 | Z20: 56 | AA20: 61 | AB20: FALSE | AD20: FALSE | AF20: Screening | AG20: Low technical fit | AH20: 2 | AI20: Boa comunicação e resposta rápida.
A21: 17 | B21: Dra. Gabriela Cardoso | C21: da-conceicaoguilherme@yahoo.com.br | D21: REQ-1024 | E21: Talent Acquisition Specialist | F21: Data | G21: Rio de Janeiro | H21: Presencial | I21: Pleno | J21: 2.7 | K21: Helena | L21: Gustavo | M21: Hunting | N21: Recruiter | O21: 45807 | P21: 45810 | Q21: FALSE | S21: FALSE | U21: FALSE | W21: FALSE | Y21: 66 | Z21: 58 | AA21: 66 | AB21: FALSE | AD21: FALSE | AF21: Rejected | AG21: No response | AH21: 3 | AI21: Apresentou aderência forte ao contexto da vaga.
A22: 18 | B22: Srta. Clara Caldeira | C22: costelamarcelo@mendes.br | D22: REQ-1068 | E22: People BP | F22: Operations | G22: Rio de Janeiro | H22: Remoto | I22: Junior | J22: 0 | K22: Stephany | L22: Fernanda | M22: Inbound | N22: TA Lead | O22: 45680 | P22: 45680 | Q22: TRUE | R22: 10 | S22: TRUE | T22: 45682 | U22: TRUE | V22: 45689 | W22: TRUE | X22: 45692 | Y22: 66 | Z22: 60 | AA22: 65 | AB22: FALSE | AD22: FALSE | AF22: Test | AG22: No response | AH22: 12 | AI22: Perfil técnico acima da média.
A23: 19 | B23: Sra. Ana Júlia Moreira | C23: barrosana-sophia@ig.com.br | D23: REQ-1094 | E23: People BP | F23: Operations | G23: Rio de Janeiro | H23: Híbrido | I23: Staff | J23: 9.2 | K23: Davi | L23: Bruno | M23: Comunidade | N23: TA Lead | O23: 45665 | P23: 45672 | Q23: TRUE | R23: 8 | S23: TRUE | T23: 45679 | U23: FALSE | W23: FALSE | Y23: 80 | Z23: 77 | AA23: 91 | AB23: FALSE | AD23: FALSE | AF23: Screening | AH23: 14 | AI23: Baixa responsividade nas etapas iniciais.
A24: 20 | B24: Juliana Teixeira | C24: halmeida@nascimento.com | D24: REQ-1082 | E24: People BP | F24: Operations | G24: Campinas | H24: Presencial | I24: Staff | J24: 7.7 | K24: Heitor | L24: Gustavo | M24: Inbound | N24: Tech Panel | O24: 45743 | P24: 45743 | Q24: TRUE | R24: 6 | S24: TRUE | T24: 45751 | U24: TRUE | V24: 45757 | W24: TRUE | X24: 45766 | Y24: 80 | Z24: 81 | AA24: 78 | AB24: TRUE | AC24: 45770 | AD24: TRUE | AE24: 45779 | AF24: Hired | AH24: 36 | AI24: Perfil técnico acima da média.
A25: 21 | B25: Emanuella Fernandes | C25: camposbryan@silva.com | D25: REQ-1023 | E25: Talent Acquisition Specialist | F25: People | G25: Campinas | H25: Híbrido | I25: Staff | J25: 11.2 | K25: Stephany | L25: Diego | M25: Github | N25: Tech Panel | O25: 45801 | P25: 45804 | Q25: FALSE | S25: FALSE | U25: FALSE | W25: FALSE | Y25: 79 | Z25: 57 | AA25: 76 | AB25: FALSE | AD25: FALSE | AF25: Rejected | AG25: No response | AH25: 3 | AI25: Pontos fortes em execução e autonomia.
A26: 22 | B26: Sra. Cecília Viana | C26: brenda33@uol.com.br | D26: REQ-1092 | E26: People BP | F26: Operations | G26: Belo Horizonte | H26: Híbrido | I26: Pleno | J26: 6 | K26: João Gabriel | L26: Ana | M26: Indicação | N26: Hiring Manager | O26: 45745 | P26: 45747 | Q26: TRUE | R26: 12 | S26: TRUE | T26: 45754 | U26: TRUE | V26: 45759 | W26: TRUE | X26: 45766 | Y26: 78 | Z26: 64 | AA26: 57 | AB26: FALSE | AD26: FALSE | AF26: Test | AG26: Accepted another offer | AH26: 21 | AI26: Apresentou aderência forte ao contexto da vaga.
A27: 23 | B27: Maria Fernanda Nogueira | C27: ncastro@melo.br | D27: REQ-1031 | E27: People BP | F27: Operations | G27: Campinas | H27: Híbrido | I27: Senior | J27: 5.3 | K27: Isabelly | L27: Carla | M27: Github | N27: Recruiter | O27: 45684 | P27: 45684 | Q27: TRUE | R27: 12 | S27: TRUE | T27: 45692 | U27: TRUE | V27: 45706 | W27: TRUE | X27: 45708 | Y27: 73 | Z27: 81 | AA27: 76 | AB27: TRUE | AC27: 45714 | AD27: TRUE | AE27: 45720 | AF27: Hired | AH27: 36 | AI27: Pediu prazo adicional para retorno.
A28: 24 | B28: Caroline Santos | C28: luiz-gustavomoraes@hotmail.com | D28: REQ-1025 | E28: Talent Acquisition Specialist | F28: Data | G28: Remote | H28: Presencial | I28: Pleno | J28: 5.3 | K28: Luna | L28: Gustavo | M28: Evento | N28: Tech Panel | O28: 45711 | P28: 45714 | Q28: FALSE | S28: FALSE | U28: FALSE | W28: FALSE | Y28: 73 | Z28: 82 | AA28: 84 | AB28: FALSE | AD28: FALSE | AF28: Rejected | AG28: No response | AH28: 3 | AI28: Pontos fortes em execução e autonomia.
A29: 25 | B29: Sr. Francisco Souza | C29: otavio73@ig.com.br | D29: REQ-1068 | E29: Analista de Recrutamento | F29: Operations | G29: Belo Horizonte | H29: Presencial | I29: Senior | J29: 7.6 | K29: Ian | L29: Fernanda | M29: Indicação | N29: Tech Panel | O29: 45726 | P29: 45728 | Q29: TRUE | R29: 2 | S29: FALSE | U29: FALSE | W29: FALSE | Y29: 83 | Z29: 98 | AA29: 94 | AB29: FALSE | AD29: FALSE | AF29: Sourced | AG29: Accepted another offer | AH29: 2 | AI29: Feedback positivo do gestor.
A30: 26 | B30: Maria Sophia Campos | C30: joao-felipe04@bol.com.br | D30: REQ-1012 | E30: Analista de Dados | F30: Tech | G30: Rio de Janeiro | H30: Remoto | I30: Junior | J30: 0.4 | K30: Diogo | L30: Gustavo | M30: LinkedIn | N30: Hiring Manager | O30: 45735 | P30: 45739 | Q30: FALSE | S30: FALSE | U30: FALSE | W30: FALSE | Y30: 63 | Z30: 72 | AA30: 76 | AB30: FALSE | AD30: FALSE | AF30: Rejected | AG30: No response | AH30: 4 | AI30: Perfil técnico acima da média.
A31: 27 | B31: Manuela Souza | C31: rcavalcanti@uol.com.br | D31: REQ-1083 | E31: People BP | F31: Operations | G31: Rio de Janeiro | H31: Remoto | I31: Junior | J31: 1.7 | K31: Ana Beatriz | L31: Carla | M31: Evento | N31: TA Lead | O31: 45709 | P31: 45712 | Q31: FALSE | S31: FALSE | U31: FALSE | W31: FALSE | Y31: 66 | Z31: 68 | AA31: 63 | AB31: FALSE | AD31: FALSE | AF31: Rejected | AG31: No response | AH31: 3 | AI31: Experiência sólida, mas expectativa salarial alta.
A32: 28 | B32: Dr. Luigi Nascimento | C32: jnogueira@ferreira.com | D32: REQ-1090 | E32: Talent Acquisition Specialist | F32: Operations | G32: Campinas | H32: Remoto | I32: Senior | J32: 7.5 | K32: Evelyn | L32: Gustavo | M32: LinkedIn | N32: Tech Panel | O32: 45699 | P32: 45702 | Q32: FALSE | S32: FALSE | U32: FALSE | W32: FALSE | Y32: 75 | Z32: 66 | AA32: 70 | AB32: FALSE | AD32: FALSE | AF32: Rejected | AG32: No response | AH32: 3 | AI32: Bom potencial de evolução.
A33: 29 | B33: Gustavo Henrique Pires | C33: cardosoyago@yahoo.com.br | D33: REQ-1048 | E33: Analista de Dados | F33: People | G33: São Paulo | H33: Presencial | I33: Pleno | J33: 3.3 | K33: Juliana | L33: Fernanda | M33: Comunidade | N33: TA Lead | O33: 45660 | P33: 45661 | Q33: TRUE | R33: 5 | S33: TRUE | T33: 45662 | U33: FALSE | W33: FALSE | Y33: 40 | Z33: 70 | AA33: 43 | AB33: FALSE | AD33: FALSE | AF33: Screening | AH33: 2 | AI33: Bom potencial de evolução.
A34: 30 | B34: Emanuelly Correia | C34: gustavo17@ig.com.br | D34: REQ-1037 | E34: Analista de Dados | F34: People | G34: São Paulo | H34: Híbrido | I34: Junior | J34: 3.5 | K34: Vinicius | L34: Diego | M34: Inbound | N34: TA Lead | O34: 45709 | P34: 45709 | Q34: TRUE | R34: 12 | S34: TRUE | T34: 45710 | U34: FALSE | W34: FALSE | Y34: 76 | Z34: 71 | AA34: 65 | AB34: FALSE | AD34: FALSE | AF34: Screening | AH34: 1 | AI34: Apresentou aderência forte ao contexto da vaga.
A35: 31 | B35: Benjamin Sales | C35: theo14@hotmail.com | D35: REQ-1070 | E35: Talent Acquisition Specialist | F35: Data | G35: Campinas | H35: Remoto | I35: Junior | J35: 3.9 | K35: Gustavo Henrique | L35: Bruno | M35: Evento | N35: Tech Panel | O35: 45786 | P35: 45790 | Q35: TRUE | R35: 6 | S35: TRUE | T35: 45799 | U35: FALSE | W35: FALSE | Y35: 71 | Z35: 82 | AA35: 86 | AB35: FALSE | AD35: FALSE | AF35: Screening | AG35: Low engagement | AH35: 13 | AI35: Boa comunicação e resposta rápida.
A36: 32 | B36: Dr. Samuel Araújo | C36: silvaluana@uol.com.br | D36: REQ-1079 | E36: Talent Acquisition Specialist | F36: People | G36: Remote | H36: Remoto | I36: Junior | J36: 4.9 | K36: João Felipe | L36: Bruno | M36: Inbound | N36: Tech Panel | O36: 45783 | P36: 45787 | Q36: TRUE | R36: 1 | S36: TRUE | T36: 45790 | U36: TRUE | V36: 45799 | W36: TRUE | X36: 45801 | Y36: 57 | Z36: 74 | AA36: 66 | AB36: FALSE | AD36: FALSE | AF36: Test | AH36: 18 | AI36: Experiência sólida, mas expectativa salarial alta.
A37: 33 | B37: Thiago Azevedo | C37: pereiraaugusto@gmail.com | D37: REQ-1045 | E37: Analista de Dados | F37: Tech | G37: Campinas | H37: Híbrido | I37: Junior | J37: 0.8 | K37: Lucas Gabriel | L37: Ana | M37: Evento | N37: TA Lead | O37: 45765 | P37: 45765 | Q37: FALSE | S37: FALSE | U37: FALSE | W37: FALSE | Y37: 60 | Z37: 84 | AA37: 66 | AB37: FALSE | AD37: FALSE | AF37: Rejected | AG37: No response | AH37: 0 | AI37: Demonstrou interesse claro na oportunidade.
A38: 34 | B38: Thiago Moraes | C38: zfreitas@bol.com.br | D38: REQ-1040 | E38: Analista de Recrutamento | F38: People | G38: Rio de Janeiro | H38: Presencial | I38: Junior | J38: 0 | K38: Benício | L38: Gustavo | M38: Github | N38: Hiring Manager | O38: 45776 | P38: 45776 | Q38: TRUE | R38: 3 | S38: TRUE | T38: 45779 | U38: TRUE | V38: 45783 | W38: TRUE | X38: 45792 | Y38: 75 | Z38: 87 | AA38: 92 | AB38: TRUE | AC38: 45796 | AD38: TRUE | AE38: 45805 | AF38: Hired | AH38: 29 | AI38: Baixa responsividade nas etapas iniciais.
A39: 35 | B39: Luiz Gustavo Moreira | C39: da-cunhajoao-gabriel@freitas.com | D39: REQ-1006 | E39: Analista de Recrutamento | F39: Tech | G39: Rio de Janeiro | H39: Híbrido | I39: Senior | J39: 6.2 | K39: Davi Lucas | L39: Bruno | M39: Hunting | N39: Tech Panel | O39: 45752 | P39: 45757 | Q39: FALSE | S39: FALSE | U39: FALSE | W39: FALSE | Y39: 98 | Z39: 90 | AA39: 84 | AB39: FALSE | AD39: FALSE | AF39: Rejected | AG39: No response | AH39: 5 | AI39: Boa comunicação e resposta rápida.
A40: 36 | B40: Maria Alice Carvalho | C40: luiza77@correia.br | D40: REQ-1007 | E40: People BP | F40: People | G40: Rio de Janeiro | H40: Remoto | I40: Pleno | J40: 3.5 | K40: Olivia | L40: Diego | M40: Inbound | N40: Recruiter | O40: 45669 | P40: 45669 | Q40: TRUE | R40: 8 | S40: FALSE | U40: FALSE | W40: FALSE | Y40: 55 | Z40: 92 | AA40: 79 | AB40: FALSE | AD40: FALSE | AF40: Sourced | AG40: Accepted another offer | AH40: 0 | AI40: Feedback positivo do gestor.
A41: 37 | B41: Rebeca Oliveira | C41: mourajoaquim@gmail.com | D41: REQ-1071 | E41: Talent Acquisition Specialist | F41: People | G41: Rio de Janeiro | H41: Remoto | I41: Pleno | J41: 5.3 | K41: Nicole | L41: Ana | M41: Comunidade | N41: Tech Panel | O41: 45777 | P41: 45777 | Q41: TRUE | R41: 11 | S41: TRUE | T41: 45786 | U41: FALSE | W41: FALSE | Y41: 45 | Z41: 75 | AA41: 45 | AB41: FALSE | AD41: FALSE | AF41: Screening | AH41: 9 | AI41: Feedback positivo do gestor.
A42: 38 | B42: Daniela Gomes | C42: rafael75@ig.com.br | D42: REQ-1068 | E42: Talent Acquisition Specialist | F42: Data | G42: Curitiba | H42: Remoto | I42: Pleno | J42: 5.3 | K42: Luiza | L42: Bruno | M42: Banco de Talentos | N42: Recruiter | O42: 45792 | P42: 45792 | Q42: TRUE | R42: 4 | S42: FALSE | U42: FALSE | W42: FALSE | Y42: 72 | Z42: 65 | AA42: 59 | AB42: FALSE | AD42: FALSE | AF42: Sourced | AG42: Culture add mismatch | AH42: 0 | AI42: Demonstrou interesse claro na oportunidade.
A43: 39 | B43: Antônio Barbosa | C43: sophiearaujo@carvalho.net | D43: REQ-1029 | E43: Analista de Dados | F43: People | G43: Remote | H43: Híbrido | I43: Pleno | J43: 1.6 | K43: Pedro Lucas | L43: Diego | M43: Hunting | N43: Recruiter | O43: 45802 | P43: 45802 | Q43: TRUE | R43: 9 | S43: TRUE | T43: 45809 | U43: TRUE | V43: 45817 | W43: TRUE | X43: 45823 | Y43: 73 | Z43: 71 | AA43: 74 | AB43: TRUE | AC43: 45825 | AD43: TRUE | AE43: 45835 | AF43: Hired | AH43: 33 | AI43: Experiência sólida, mas expectativa salarial alta.
A44: 40 | B44: Dra. Lara Dias | C44: paulomelo@hotmail.com | D44: REQ-1001 | E44: Talent Acquisition Specialist | F44: People | G44: Remote | H44: Híbrido | I44: Staff | J44: 9.3 | K44: Natália | L44: Diego | M44: Banco de Talentos | N44: TA Lead | O44: 45806 | P44: 45806 | Q44: TRUE | R44: 8 | S44: FALSE | U44: FALSE | W44: FALSE | Y44: 66 | Z44: 93 | AA44: 72 | AB44: FALSE | AD44: FALSE | AF44: Sourced | AH44: 0 | AI44: Baixa responsividade nas etapas iniciais.
A45: 41 | B45: Pedro Melo | C45: zda-mata@uol.com.br | D45: REQ-1026 | E45: Analista de Dados | F45: People | G45: Campinas | H45: Híbrido | I45: Senior | J45: 6.5 | K45: Sarah | L45: Gustavo | M45: Evento | N45: Hiring Manager | O45: 45787 | P45: 45787 | Q45: TRUE | R45: 0 | S45: FALSE | U45: FALSE | W45: FALSE | Y45: 100 | Z45: 100 | AA45: 96 | AB45: FALSE | AD45: FALSE | AF45: Sourced | AH45: 0 | AI45: Bom potencial de evolução.
A46: 42 | B46: Diego Araújo | C46: da-cunhaarthur@rodrigues.org | D46: REQ-1066 | E46: People BP | F46: People | G46: Rio de Janeiro | H46: Híbrido | I46: Staff | J46: 10.7 | K46: Alice | L46: Bruno | M46: Comunidade | N46: TA Lead | O46: 45694 | P46: 45694 | Q46: FALSE | S46: FALSE | U46: FALSE | W46: FALSE | Y46: 55 | Z46: 79 | AA46: 69 | AB46: FALSE | AD46: FALSE | AF46: Rejected | AG46: No response | AH46: 0 | AI46: Pediu prazo adicional para retorno.
A47: 43 | B47: Maitê Carvalho | C47: gviana@bol.com.br | D47: REQ-1064 | E47: Talent Acquisition Specialist | F47: People | G47: Remote | H47: Híbrido | I47: Senior | J47: 7.2 | K47: Helena | L47: Ana | M47: Comunidade | N47: Hiring Manager | O47: 45685 | P47: 45690 | Q47: FALSE | S47: FALSE | U47: FALSE | W47: FALSE | Y47: 73 | Z47: 81 | AA47: 78 | AB47: FALSE | AD47: FALSE | AF47: Rejected | AG47: No response | AH47: 5 | AI47: Baixa responsividade nas etapas iniciais.
A48: 44 | B48: Daniel Moura | C48: emanuelda-cruz@bol.com.br | D48: REQ-1036 | E48: Talent Acquisition Specialist | F48: Operations | G48: Belo Horizonte | H48: Presencial | I48: Pleno | J48: 6.3 | K48: Bianca | L48: Gustavo | M48: Banco de Talentos | N48: Tech Panel | O48: 45774 | P48: 45774 | Q48: TRUE | R48: 4 | S48: TRUE | T48: 45778 | U48: TRUE | V48: 45788 | W48: TRUE | X48: 45795 | Y48: 92 | Z48: 57 | AA48: 78 | AB48: FALSE | AD48: FALSE | AF48: Test | AG48: No response | AH48: 21 | AI48: Apresentou aderência forte ao contexto da vaga.
A49: 45 | B49: Carlos Eduardo Moura | C49: da-cruznathan@yahoo.com.br | D49: REQ-1007 | E49: Analista de Dados | F49: Operations | G49: Curitiba | H49: Híbrido | I49: Junior | J49: 2.6 | K49: Luiz Otávio | L49: Fernanda | M49: Hunting | N49: Recruiter | O49: 45774 | P49: 45776 | Q49: TRUE | R49: 11 | S49: TRUE | T49: 45786 | U49: TRUE | V49: 45788 | W49: FALSE | Y49: 56 | Z49: 57 | AA49: 52 | AB49: FALSE | AD49: FALSE | AF49: Interview | AG49: Failed technical test | AH49: 14 | AI49: Apresentou aderência forte ao contexto da vaga.
A50: 46 | B50: Juan Fernandes | C50: maitealmeida@bol.com.br | D50: REQ-1021 | E50: People BP | F50: Tech | G50: Remote | H50: Remoto | I50: Pleno | J50: 7.4 | K50: Ana Luiza | L50: Ana | M50: Evento | N50: Tech Panel | O50: 45721 | P50: 45724 | Q50: TRUE | R50: 0 | S50: TRUE | T50: 45730 | U50: TRUE | V50: 45742 | W50: TRUE | X50: 45744 | Y50: 72 | Z50: 86 | AA50: 72 | AB50: TRUE | AC50: 45751 | AD50: TRUE | AE50: 45762 | AF50: Hired | AH50: 41 | AI50: Demonstrou interesse claro na oportunidade.
A51: 47 | B51: Nina da Mata | C51: pintoluna@da.br | D51: REQ-1033 | E51: Analista de Dados | F51: Operations | G51: Belo Horizonte | H51: Presencial | I51: Staff | J51: 11 | K51: Marcela | L51: Fernanda | M51: Github | N51: Hiring Manager | O51: 45729 | P51: 45733 | Q51: TRUE | R51: 10 | S51: FALSE | U51: FALSE | W51: FALSE | Y51: 63 | Z51: 88 | AA51: 88 | AB51: FALSE | AD51: FALSE | AF51: Sourced | AH51: 4 | AI51: Pontos fortes em execução e autonomia.
A52: 48 | B52: Henrique Cavalcanti | C52: leandro97@hotmail.com | D52: REQ-1017 | E52: Analista de Dados | F52: Data | G52: São Paulo | H52: Presencial | I52: Junior | J52: 2.2 | K52: Francisco | L52: Gustavo | M52: Banco de Talentos | N52: Hiring Manager | O52: 45778 | P52: 45778 | Q52: TRUE | R52: 3 | S52: TRUE | T52: 45780 | U52: TRUE | V52: 45783 | W52: TRUE | X52: 45793 | Y52: 67 | Z52: 69 | AA52: 75 | AB52: FALSE | AD52: FALSE | AF52: Test | AG52: Low technical fit | AH52: 15 | AI52: Apresentou aderência forte ao contexto da vaga.
A53: 49 | B53: Rodrigo Novaes | C53: maria-ceciliaaraujo@silva.com | D53: REQ-1011 | E53: Analista de Dados | F53: Tech | G53: Curitiba | H53: Presencial | I53: Senior | J53: 9.6 | K53: Fernanda | L53: Carla | M53: Hunting | N53: Recruiter | O53: 45704 | P53: 45706 | Q53: TRUE | R53: 4 | S53: TRUE | T53: 45708 | U53: TRUE | V53: 45712 | W53: TRUE | X53: 45714 | Y53: 89 | Z53: 62 | AA53: 71 | AB53: FALSE | AD53: FALSE | AF53: Test | AH53: 10 | AI53: Pontos fortes em execução e autonomia.
A54: 50 | B54: Kaique Correia | C54: lais23@ig.com.br | D54: REQ-1032 | E54: People BP | F54: Operations | G54: Curitiba | H54: Híbrido | I54: Pleno | J54: 4 | K54: Guilherme | L54: Diego | M54: Comunidade | N54: Recruiter | O54: 45805 | P54: 45805 | Q54: FALSE | S54: FALSE | U54: FALSE | W54: FALSE | Y54: 89 | Z54: 69 | AA54: 94 | AB54: FALSE | AD54: FALSE | AF54: Rejected | AG54: No response | AH54: 0 | AI54: Perfil técnico acima da média.
A55: 51 | B55: Yago Sales | C55: kamilly83@nunes.br | D55: REQ-1074 | E55: People BP | F55: People | G55: Rio de Janeiro | H55: Híbrido | I55: Senior | J55: 7.2 | K55: Emanuella | L55: Diego | M55: Comunidade | N55: Tech Panel | O55: 45739 | P55: 45739 | Q55: TRUE | R55: 2 | S55: FALSE | U55: FALSE | W55: FALSE | Y55: 67 | Z55: 70 | AA55: 75 | AB55: FALSE | AD55: FALSE | AF55: Sourced | AG55: Low technical fit | AH55: 0 | AI55: Bom potencial de evolução.
A56: 52 | B56: Alice da Paz | C56: da-rochayuri@correia.com | D56: REQ-1015 | E56: Talent Acquisition Specialist | F56: Data | G56: São Paulo | H56: Remoto | I56: Junior | J56: 3.4 | K56: Marina | L56: Ana | M56: LinkedIn | N56: Tech Panel | O56: 45730 | P56: 45733 | Q56: TRUE | R56: 4 | S56: TRUE | T56: 45736 | U56: FALSE | W56: FALSE | Y56: 88 | Z56: 79 | AA56: 90 | AB56: FALSE | AD56: FALSE | AF56: Screening | AG56: Timing mismatch | AH56: 6 | AI56: Boa comunicação e resposta rápida.
A57: 53 | B57: Luiz Miguel Moraes | C57: otavioporto@campos.com | D57: REQ-1069 | E57: Analista de Recrutamento | F57: Data | G57: Curitiba | H57: Remoto | I57: Junior | J57: 1.3 | K57: Gabriela | L57: Carla | M57: Comunidade | N57: Recruiter | O57: 45742 | P57: 45746 | Q57: FALSE | S57: FALSE | U57: FALSE | W57: FALSE | Y57: 83 | Z57: 63 | AA57: 69 | AB57: FALSE | AD57: FALSE | AF57: Rejected | AG57: No response | AH57: 4 | AI57: Boa comunicação e resposta rápida.
A58: 54 | B58: Stephany Fogaça | C58: gustavo83@ig.com.br | D58: REQ-1004 | E58: People BP | F58: Operations | G58: Rio de Janeiro | H58: Híbrido | I58: Senior | J58: 6.9 | K58: Alexandre | L58: Fernanda | M58: Github | N58: Hiring Manager | O58: 45776 | P58: 45783 | Q58: TRUE | R58: 1 | S58: TRUE | T58: 45785 | U58: TRUE | V58: 45795 | W58: TRUE | X58: 45804 | Y58: 70 | Z58: 87 | AA58: 78 | AB58: FALSE | AD58: FALSE | AF58: Test | AH58: 28 | AI58: Experiência sólida, mas expectativa salarial alta.
A59: 55 | B59: Juan Ramos | C59: xfernandes@ig.com.br | D59: REQ-1095 | E59: Talent Acquisition Specialist | F59: People | G59: Curitiba | H59: Remoto | I59: Senior | J59: 8.9 | K59: Ana Vitória | L59: Carla | M59: Indicação | N59: Recruiter | O59: 45737 | P59: 45739 | Q59: TRUE | R59: 0 | S59: TRUE | T59: 45746 | U59: FALSE | W59: FALSE | Y59: 76 | Z59: 98 | AA59: 71 | AB59: FALSE | AD59: FALSE | AF59: Screening | AG59: Failed technical test | AH59: 9 | AI59: Baixa responsividade nas etapas iniciais.
A60: 56 | B60: Cauã Dias | C60: souzalavinia@gmail.com | D60: REQ-1091 | E60: People BP | F60: Data | G60: Remote | H60: Remoto | I60: Senior | J60: 9.4 | K60: Maria Fernanda | L60: Bruno | M60: Github | N60: Recruiter | O60: 45745 | P60: 45745 | Q60: TRUE | R60: 6 | S60: TRUE | T60: 45746 | U60: TRUE | V60: 45753 | W60: TRUE | X60: 45758 | Y60: 75 | Z60: 85 | AA60: 100 | AB60: TRUE | AC60: 45761 | AD60: TRUE | AE60: 45770 | AF60: Hired | AH60: 25 | AI60: Demonstrou interesse claro na oportunidade.
A61: 57 | B61: Caio Pires | C61: ana-julialopes@gmail.com | D61: REQ-1003 | E61: Analista de Recrutamento | F61: Tech | G61: Rio de Janeiro | H61: Presencial | I61: Pleno | J61: 5.2 | K61: Otávio | L61: Ana | M61: LinkedIn | N61: Hiring Manager | O61: 45673 | P61: 45678 | Q61: TRUE | R61: 6 | S61: TRUE | T61: 45685 | U61: TRUE | V61: 45697 | W61: FALSE | Y61: 77 | Z61: 63 | AA61: 66 | AB61: FALSE | AD61: FALSE | AF61: Interview | AH61: 24 | AI61: Experiência sólida, mas expectativa salarial alta.
A62: 58 | B62: Kevin Lopes | C62: benicio44@yahoo.com.br | D62: REQ-1017 | E62: Analista de Recrutamento | F62: Operations | G62: Belo Horizonte | H62: Remoto | I62: Senior | J62: 6.8 | K62: Benício | L62: Fernanda | M62: Comunidade | N62: Hiring Manager | O62: 45808 | P62: 45812 | Q62: TRUE | R62: 9 | S62: TRUE | T62: 45814 | U62: FALSE | W62: FALSE | Y62: 55 | Z62: 86 | AA62: 71 | AB62: FALSE | AD62: FALSE | AF62: Screening | AG62: Accepted another offer | AH62: 6 | AI62: Pediu prazo adicional para retorno.
A63: 59 | B63: Pedro Lucas Aragão | C63: scosta@yahoo.com.br | D63: REQ-1051 | E63: Analista de Dados | F63: People | G63: Campinas | H63: Híbrido | I63: Senior | J63: 6.1 | K63: Davi Luiz | L63: Carla | M63: LinkedIn | N63: Hiring Manager | O63: 45801 | P63: 45809 | Q63: FALSE | S63: FALSE | U63: FALSE | W63: FALSE | Y63: 80 | Z63: 78 | AA63: 74 | AB63: FALSE | AD63: FALSE | AF63: Rejected | AG63: No response | AH63: 8 | AI63: Demonstrou interesse claro na oportunidade.
A64: 60 | B64: Ana Carolina Nascimento | C64: maria-clarada-cruz@bol.com.br | D64: REQ-1038 | E64: People BP | F64: Tech | G64: Belo Horizonte | H64: Híbrido | I64: Junior | J64: 2.8 | K64: Vitor | L64: Gustavo | M64: Inbound | N64: Tech Panel | O64: 45722 | P64: 45724 | Q64: TRUE | R64: 3 | S64: TRUE | T64: 45725 | U64: TRUE | V64: 45736 | W64: TRUE | X64: 45739 | Y64: 100 | Z64: 85 | AA64: 100 | AB64: TRUE | AC64: 45746 | AD64: FALSE | AF64: Offer | AH64: 24 | AI64: Demonstrou interesse claro na oportunidade.
A65: 61 | B65: João Vitor Rodrigues | C65: xnunes@cardoso.com | D65: REQ-1017 | E65: Analista de Dados | F65: Operations | G65: Curitiba | H65: Híbrido | I65: Pleno | J65: 4.3 | K65: Leonardo | L65: Carla | M65: Github | N65: Tech Panel | O65: 45675 | P65: 45676 | Q65: FALSE | S65: FALSE | U65: FALSE | W65: FALSE | Y65: 90 | Z65: 76 | AA65: 89 | AB65: FALSE | AD65: FALSE | AF65: Rejected | AG65: No response | AH65: 1 | AI65: Demonstrou interesse claro na oportunidade.
A66: 62 | B66: Sabrina Dias | C66: anthony36@yahoo.com.br | D66: REQ-1088 | E66: Analista de Recrutamento | F66: Data | G66: Remote | H66: Presencial | I66: Senior | J66: 10.4 | K66: Augusto | L66: Diego | M66: Comunidade | N66: Tech Panel | O66: 45736 | P66: 45739 | Q66: FALSE | S66: FALSE | U66: FALSE | W66: FALSE | Y66: 80 | Z66: 89 | AA66: 76 | AB66: FALSE | AD66: FALSE | AF66: Rejected | AG66: No response | AH66: 3 | AI66: Experiência sólida, mas expectativa salarial alta.
A67: 63 | B67: Maitê Mendes | C67: peixotomaria-luiza@ig.com.br | D67: REQ-1042 | E67: Talent Acquisition Specialist | F67: People | G67: Rio de Janeiro | H67: Presencial | I67: Pleno | J67: 4 | K67: Ana | L67: Fernanda | M67: Evento | N67: TA Lead | O67: 45747 | P67: 45751 | Q67: FALSE | S67: FALSE | U67: FALSE | W67: FALSE | Y67: 67 | Z67: 66 | AA67: 69 | AB67: FALSE | AD67: FALSE | AF67: Rejected | AG67: No response | AH67: 4 | AI67: Perfil técnico acima da média.
A68: 64 | B68: Larissa da Mota | C68: cavalcantidiego@goncalves.net | D68: REQ-1056 | E68: People BP | F68: People | G68: Belo Horizonte | H68: Remoto | I68: Senior | J68: 7.6 | K68: Isabelly | L68: Diego | M68: Banco de Talentos | N68: Recruiter | O68: 45684 | P68: 45689 | Q68: TRUE | R68: 0 | S68: TRUE | T68: 45692 | U68: TRUE | V68: 45705 | W68: TRUE | X68: 45706 | Y68: 55 | Z68: 59 | AA68: 49 | AB68: FALSE | AD68: FALSE | AF68: Test | AH68: 22 | AI68: Pontos fortes em execução e autonomia.
A69: 65 | B69: Dr. Enzo Gabriel Rezende | C69: francisco85@caldeira.com | D69: REQ-1087 | E69: Talent Acquisition Specialist | F69: People | G69: Campinas | H69: Presencial | I69: Pleno | J69: 3.7 | K69: Renan | L69: Diego | M69: Indicação | N69: Tech Panel | O69: 45710 | P69: 45710 | Q69: FALSE | S69: FALSE | U69: FALSE | W69: FALSE | Y69: 75 | Z69: 75 | AA69: 76 | AB69: FALSE | AD69: FALSE | AF69: Rejected | AG69: No response | AH69: 0 | AI69: Pediu prazo adicional para retorno.
A70: 66 | B70: Kevin Nascimento | C70: brunovieira@gmail.com | D70: REQ-1086 | E70: Talent Acquisition Specialist | F70: Operations | G70: Belo Horizonte | H70: Presencial | I70: Pleno | J70: 4.7 | K70: Ana Beatriz | L70: Carla | M70: Indicação | N70: Tech Panel | O70: 45706 | P70: 45713 | Q70: TRUE | R70: 8 | S70: FALSE | U70: FALSE | W70: FALSE | Y70: 81 | Z70: 90 | AA70: 92 | AB70: FALSE | AD70: FALSE | AF70: Sourced | AH70: 7 | AI70: Perfil técnico acima da média.
A71: 67 | B71: Maria Sophia Pereira | C71: juliada-cunha@nunes.com | D71: REQ-1000 | E71: Analista de Dados | F71: Operations | G71: Remote | H71: Remoto | I71: Senior | J71: 7.3 | K71: Sarah | L71: Carla | M71: LinkedIn | N71: Recruiter | O71: 45727 | P71: 45737 | Q71: FALSE | S71: FALSE | U71: FALSE | W71: FALSE | Y71: 71 | Z71: 79 | AA71: 86 | AB71: FALSE | AD71: FALSE | AF71: Rejected | AG71: No response | AH71: 10 | AI71: Pediu prazo adicional para retorno.
A72: 68 | B72: Ryan Monteiro | C72: yagoaragao@rodrigues.br | D72: REQ-1092 | E72: Analista de Dados | F72: Operations | G72: Rio de Janeiro | H72: Remoto | I72: Senior | J72: 10.1 | K72: Clarice | L72: Fernanda | M72: Github | N72: TA Lead | O72: 45789 | P72: 45789 | Q72: TRUE | R72: 0 | S72: TRUE | T72: 45797 | U72: FALSE | W72: FALSE | Y72: 77 | Z72: 80 | AA72: 78 | AB72: FALSE | AD72: FALSE | AF72: Screening | AH72: 8 | AI72: Demonstrou interesse claro na oportunidade.
A73: 69 | B73: Arthur Lima | C73: bfreitas@castro.com | D73: REQ-1005 | E73: Analista de Dados | F73: Operations | G73: Campinas | H73: Remoto | I73: Senior | J73: 5 | K73: Brenda | L73: Ana | M73: Inbound | N73: Hiring Manager | O73: 45770 | P73: 45770 | Q73: FALSE | S73: FALSE | U73: FALSE | W73: FALSE | Y73: 73 | Z73: 90 | AA73: 84 | AB73: FALSE | AD73: FALSE | AF73: Rejected | AG73: No response | AH73: 0 | AI73: Baixa responsividade nas etapas iniciais.
A74: 70 | B74: João Guilherme Lima | C74: halves@cunha.br | D74: REQ-1030 | E74: Analista de Recrutamento | F74: Tech | G74: Rio de Janeiro | H74: Híbrido | I74: Junior | J74: 4.3 | K74: Bárbara | L74: Bruno | M74: Comunidade | N74: Hiring Manager | O74: 45659 | P74: 45659 | Q74: TRUE | R74: 5 | S74: TRUE | T74: 45665 | U74: FALSE | W74: FALSE | Y74: 94 | Z74: 62 | AA74: 65 | AB74: FALSE | AD74: FALSE | AF74: Screening | AH74: 6 | AI74: Baixa responsividade nas etapas iniciais.
A75: 71 | B75: Ana Sophia Fernandes | C75: usales@yahoo.com.br | D75: REQ-1062 | E75: Talent Acquisition Specialist | F75: Tech | G75: Campinas | H75: Presencial | I75: Pleno | J75: 2.9 | K75: Thales | L75: Ana | M75: Inbound | N75: Tech Panel | O75: 45708 | P75: 45708 | Q75: TRUE | R75: 4 | S75: FALSE | U75: FALSE | W75: FALSE | Y75: 56 | Z75: 89 | AA75: 70 | AB75: FALSE | AD75: FALSE | AF75: Sourced | AH75: 0 | AI75: Baixa responsividade nas etapas iniciais.
A76: 72 | B76: Rafael Ramos | C76: da-conceicaobryan@yahoo.com.br | D76: REQ-1087 | E76: Analista de Recrutamento | F76: People | G76: Remote | H76: Híbrido | I76: Junior | J76: 5.2 | K76: Mariana | L76: Bruno | M76: Inbound | N76: Tech Panel | O76: 45782 | P76: 45783 | Q76: TRUE | R76: 8 | S76: TRUE | T76: 45786 | U76: TRUE | V76: 45789 | W76: TRUE | X76: 45793 | Y76: 60 | Z76: 68 | AA76: 64 | AB76: FALSE | AD76: FALSE | AF76: Test | AH76: 11 | AI76: Baixa responsividade nas etapas iniciais.
A77: 73 | B77: Antônio Lopes | C77: icarvalho@uol.com.br | D77: REQ-1055 | E77: Talent Acquisition Specialist | F77: Tech | G77: Rio de Janeiro | H77: Remoto | I77: Pleno | J77: 3.1 | K77: Enrico | L77: Gustavo | M77: Banco de Talentos | N77: Tech Panel | O77: 45781 | P77: 45787 | Q77: TRUE | R77: 2 | S77: TRUE | T77: 45796 | U77: TRUE | V77: 45805 | W77: TRUE | X77: 45809 | Y77: 62 | Z77: 79 | AA77: 50 | AB77: FALSE | AD77: FALSE | AF77: Test | AG77: Headcount closed | AH77: 28 | AI77: Feedback positivo do gestor.
A78: 74 | B78: Eduarda Jesus | C78: glopes@bol.com.br | D78: REQ-1026 | E78: Talent Acquisition Specialist | F78: Data | G78: Campinas | H78: Presencial | I78: Pleno | J78: 4.8 | K78: Lucas | L78: Diego | M78: Evento | N78: Tech Panel | O78: 45753 | P78: 45753 | Q78: TRUE | R78: 2 | S78: FALSE | U78: FALSE | W78: FALSE | Y78: 66 | Z78: 75 | AA78: 53 | AB78: FALSE | AD78: FALSE | AF78: Sourced | AH78: 0 | AI78: Baixa responsividade nas etapas iniciais.
A79: 75 | B79: Dra. Brenda da Cunha | C79: gabriellysales@cardoso.net | D79: REQ-1076 | E79: Analista de Dados | F79: Tech | G79: Rio de Janeiro | H79: Remoto | I79: Senior | J79: 7.9 | K79: Bernardo | L79: Fernanda | M79: Comunidade | N79: Recruiter | O79: 45712 | P79: 45713 | Q79: TRUE | R79: 2 | S79: TRUE | T79: 45714 | U79: FALSE | W79: FALSE | Y79: 85 | Z79: 82 | AA79: 93 | AB79: FALSE | AD79: FALSE | AF79: Screening | AG79: Salary mismatch | AH79: 2 | AI79: Demonstrou interesse claro na oportunidade.
A80: 76 | B80: Dr. Benjamin Pereira | C80: xmoura@cavalcanti.com | D80: REQ-1080 | E80: Analista de Dados | F80: People | G80: São Paulo | H80: Híbrido | I80: Pleno | J80: 4.8 | K80: João Felipe | L80: Carla | M80: LinkedIn | N80: TA Lead | O80: 45766 | P80: 45772 | Q80: TRUE | R80: 9 | S80: TRUE | T80: 45776 | U80: TRUE | V80: 45789 | W80: TRUE | X80: 45794 | Y80: 67 | Z80: 63 | AA80: 43 | AB80: FALSE | AD80: FALSE | AF80: Test | AH80: 28 | AI80: Experiência sólida, mas expectativa salarial alta.
A81: 77 | B81: Dr. Yuri da Mota | C81: mourapedro@ig.com.br | D81: REQ-1005 | E81: People BP | F81: Operations | G81: Curitiba | H81: Presencial | I81: Pleno | J81: 4 | K81: Maria Sophia | L81: Fernanda | M81: Hunting | N81: Tech Panel | O81: 45742 | P81: 45744 | Q81: TRUE | R81: 11 | S81: TRUE | T81: 45754 | U81: TRUE | V81: 45763 | W81: TRUE | X81: 45772 | Y81: 63 | Z81: 73 | AA81: 65 | AB81: FALSE | AD81: FALSE | AF81: Test | AH81: 30 | AI81: Baixa responsividade nas etapas iniciais.
A82: 78 | B82: Pedro Henrique Almeida | C82: gabrielamoraes@barros.com | D82: REQ-1017 | E82: Analista de Dados | F82: Tech | G82: Curitiba | H82: Remoto | I82: Senior | J82: 4.8 | K82: Carlos Eduardo | L82: Bruno | M82: Github | N82: Hiring Manager | O82: 45774 | P82: 45774 | Q82: FALSE | S82: FALSE | U82: FALSE | W82: FALSE | Y82: 82 | Z82: 69 | AA82: 60 | AB82: FALSE | AD82: FALSE | AF82: Rejected | AG82: No response | AH82: 0 | AI82: Demonstrou interesse claro na oportunidade.
A83: 79 | B83: Fernanda da Cunha | C83: mirella71@rocha.com | D83: REQ-1000 | E83: People BP | F83: Data | G83: São Paulo | H83: Presencial | I83: Senior | J83: 5.1 | K83: Vitor Hugo | L83: Diego | M83: Inbound | N83: Hiring Manager | O83: 45803 | P83: 45808 | Q83: TRUE | R83: 6 | S83: FALSE | U83: FALSE | W83: FALSE | Y83: 73 | Z83: 67 | AA83: 74 | AB83: FALSE | AD83: FALSE | AF83: Sourced | AH83: 5 | AI83: Baixa responsividade nas etapas iniciais.
A84: 80 | B84: Lucas Gabriel Nascimento | C84: camilacampos@da.br | D84: REQ-1072 | E84: Analista de Dados | F84: Data | G84: Curitiba | H84: Presencial | I84: Pleno | J84: 3.5 | K84: Maria Fernanda | L84: Diego | M84: Evento | N84: Tech Panel | O84: 45690 | P84: 45693 | Q84: TRUE | R84: 4 | S84: TRUE | T84: 45699 | U84: TRUE | V84: 45707 | W84: TRUE | X84: 45714 | Y84: 57 | Z84: 85 | AA84: 57 | AB84: FALSE | AD84: FALSE | AF84: Test | AH84: 24 | AI84: Apresentou aderência forte ao contexto da vaga.
A85: 81 | B85: Emilly Moreira | C85: fnunes@teixeira.com | D85: REQ-1032 | E85: Analista de Recrutamento | F85: Data | G85: Curitiba | H85: Remoto | I85: Junior | J85: 3.4 | K85: Rafael | L85: Ana | M85: Banco de Talentos | N85: Hiring Manager | O85: 45708 | P85: 45708 | Q85: TRUE | R85: 4 | S85: TRUE | T85: 45713 | U85: TRUE | V85: 45715 | W85: TRUE | X85: 45725 | Y85: 70 | Z85: 77 | AA85: 65 | AB85: FALSE | AD85: FALSE | AF85: Test | AG85: Accepted another offer | AH85: 17 | AI85: Demonstrou interesse claro na oportunidade.
A86: 82 | B86: Mariana Lima | C86: omartins@porto.com | D86: REQ-1024 | E86: People BP | F86: Tech | G86: Campinas | H86: Remoto | I86: Staff | J86: 11.2 | K86: Ana Júlia | L86: Bruno | M86: Comunidade | N86: Tech Panel | O86: 45801 | P86: 45804 | Q86: TRUE | R86: 2 | S86: TRUE | T86: 45810 | U86: TRUE | V86: 45823 | W86: FALSE | Y86: 59 | Z86: 88 | AA86: 70 | AB86: FALSE | AD86: FALSE | AF86: Interview | AG86: Low technical fit | AH86: 22 | AI86: Pediu prazo adicional para retorno.
A87: 83 | B87: Marcela Lopes | C87: gomeseloah@dias.net | D87: REQ-1090 | E87: Analista de Recrutamento | F87: Operations | G87: Curitiba | H87: Remoto | I87: Junior | J87: 4 | K87: Carolina | L87: Gustavo | M87: Github | N87: Recruiter | O87: 45665 | P87: 45668 | Q87: FALSE | S87: FALSE | U87: FALSE | W87: FALSE | Y87: 46 | Z87: 56 | AA87: 37 | AB87: FALSE | AD87: FALSE | AF87: Rejected | AG87: No response | AH87: 3 | AI87: Apresentou aderência forte ao contexto da vaga.
A88: 84 | B88: Maysa Souza | C88: ada-cruz@costela.net | D88: REQ-1041 | E88: Analista de Recrutamento | F88: Data | G88: Campinas | H88: Remoto | I88: Senior | J88: 5.2 | K88: Ana Clara | L88: Bruno | M88: Comunidade | N88: TA Lead | O88: 45738 | P88: 45740 | Q88: TRUE | R88: 8 | S88: TRUE | T88: 45742 | U88: TRUE | V88: 45752 | W88: FALSE | Y88: 59 | Z88: 71 | AA88: 60 | AB88: FALSE | AD88: FALSE | AF88: Interview | AG88: Low technical fit | AH88: 14 | AI88: Feedback positivo do gestor.
A89: 85 | B89: Lara Nogueira | C89: laviniamoreira@bol.com.br | D89: REQ-1094 | E89: People BP | F89: People | G89: Remote | H89: Híbrido | I89: Pleno | J89: 3.8 | K89: Sofia | L89: Carla | M89: Evento | N89: Hiring Manager | O89: 45769 | P89: 45769 | Q89: TRUE | R89: 11 | S89: TRUE | T89: 45773 | U89: TRUE | V89: 45787 | W89: TRUE | X89: 45790 | Y89: 76 | Z89: 92 | AA89: 100 | AB89: TRUE | AC89: 45796 | AD89: FALSE | AF89: Offer | AH89: 27 | AI89: Perfil técnico acima da média.
A90: 86 | B90: Levi Porto | C90: mendesantonio@bol.com.br | D90: REQ-1072 | E90: People BP | F90: Data | G90: Rio de Janeiro | H90: Remoto | I90: Senior | J90: 8.3 | K90: Yasmin | L90: Bruno | M90: Evento | N90: Hiring Manager | O90: 45671 | P90: 45676 | Q90: TRUE | R90: 3 | S90: TRUE | T90: 45683 | U90: TRUE | V90: 45686 | W90: TRUE | X90: 45695 | Y90: 79 | Z90: 71 | AA90: 75 | AB90: FALSE | AD90: FALSE | AF90: Test | AG90: Culture add mismatch | AH90: 24 | AI90: Baixa responsividade nas etapas iniciais.
A91: 87 | B91: Lorena Vieira | C91: daniela53@uol.com.br | D91: REQ-1003 | E91: Analista de Recrutamento | F91: People | G91: Belo Horizonte | H91: Híbrido | I91: Senior | J91: 6.4 | K91: Letícia | L91: Carla | M91: Banco de Talentos | N91: Hiring Manager | O91: 45709 | P91: 45709 | Q91: TRUE | R91: 5 | S91: TRUE | T91: 45713 | U91: TRUE | V91: 45721 | W91: TRUE | X91: 45724 | Y91: 87 | Z91: 87 | AA91: 75 | AB91: TRUE | AC91: 45725 | AD91: TRUE | AE91: 45732 | AF91: Hired | AH91: 23 | AI91: Pediu prazo adicional para retorno.
A92: 88 | B92: Ana Clara Caldeira | C92: sda-rocha@santos.com | D92: REQ-1022 | E92: Analista de Recrutamento | F92: Tech | G92: Belo Horizonte | H92: Presencial | I92: Junior | J92: 2.8 | K92: Luiza | L92: Gustavo | M92: Github | N92: TA Lead | O92: 45663 | P92: 45665 | Q92: TRUE | R92: 3 | S92: TRUE | T92: 45666 | U92: TRUE | V92: 45670 | W92: TRUE | X92: 45677 | Y92: 92 | Z92: 75 | AA92: 78 | AB92: TRUE | AC92: 45684 | AD92: TRUE | AE92: 45690 | AF92: Hired | AH92: 27 | AI92: Experiência sólida, mas expectativa salarial alta.
A93: 89 | B93: Benjamin Freitas | C93: davi-luccapeixoto@bol.com.br | D93: REQ-1088 | E93: People BP | F93: People | G93: Remote | H93: Remoto | I93: Pleno | J93: 4 | K93: Lucas | L93: Gustavo | M93: Banco de Talentos | N93: Tech Panel | O93: 45705 | P93: 45707 | Q93: TRUE | R93: 0 | S93: TRUE | T93: 45712 | U93: FALSE | W93: FALSE | Y93: 68 | Z93: 72 | AA93: 77 | AB93: FALSE | AD93: FALSE | AF93: Screening | AH93: 7 | AI93: Perfil técnico acima da média.
A94: 90 | B94: Alana da Mata | C94: felipe55@uol.com.br | D94: REQ-1090 | E94: Analista de Dados | F94: Operations | G94: Curitiba | H94: Híbrido | I94: Senior | J94: 6 | K94: Davi Lucca | L94: Bruno | M94: Github | N94: TA Lead | O94: 45681 | P94: 45685 | Q94: TRUE | R94: 2 | S94: TRUE | T94: 45694 | U94: FALSE | W94: FALSE | Y94: 62 | Z94: 61 | AA94: 59 | AB94: FALSE | AD94: FALSE | AF94: Screening | AG94: Low engagement | AH94: 13 | AI94: Feedback positivo do gestor.
A95: 91 | B95: Otávio Martins | C95: pintojulia@ig.com.br | D95: REQ-1033 | E95: Talent Acquisition Specialist | F95: Data | G95: São Paulo | H95: Remoto | I95: Senior | J95: 7.4 | K95: Eloah | L95: Ana | M95: LinkedIn | N95: Hiring Manager | O95: 45661 | P95: 45661 | Q95: FALSE | S95: FALSE | U95: FALSE | W95: FALSE | Y95: 60 | Z95: 82 | AA95: 75 | AB95: FALSE | AD95: FALSE | AF95: Rejected | AG95: No response | AH95: 0 | AI95: Pontos fortes em execução e autonomia.
A96: 92 | B96: Ana Julia Ferreira | C96: goncalvesclarice@yahoo.com.br | D96: REQ-1083 | E96: Analista de Dados | F96: Tech | G96: Remote | H96: Híbrido | I96: Senior | J96: 6.5 | K96: Raquel | L96: Bruno | M96: Banco de Talentos | N96: Hiring Manager | O96: 45702 | P96: 45711 | Q96: FALSE | S96: FALSE | U96: FALSE | W96: FALSE | Y96: 85 | Z96: 78 | AA96: 81 | AB96: FALSE | AD96: FALSE | AF96: Rejected | AG96: No response | AH96: 9 | AI96: Experiência sólida, mas expectativa salarial alta.
A97: 93 | B97: Nicole Cavalcanti | C97: duarteantonio@bol.com.br | D97: REQ-1035 | E97: Analista de Recrutamento | F97: People | G97: Curitiba | H97: Presencial | I97: Senior | J97: 6.6 | K97: Gabrielly | L97: Diego | M97: Inbound | N97: Hiring Manager | O97: 45792 | P97: 45794 | Q97: TRUE | R97: 11 | S97: FALSE | U97: FALSE | W97: FALSE | Y97: 73 | Z97: 74 | AA97: 70 | AB97: FALSE | AD97: FALSE | AF97: Sourced | AH97: 2 | AI97: Demonstrou interesse claro na oportunidade.
A98: 94 | B98: Benício Rodrigues | C98: ana-livia76@gmail.com | D98: REQ-1080 | E98: Analista de Dados | F98: People | G98: Campinas | H98: Presencial | I98: Pleno | J98: 5.9 | K98: Felipe | L98: Carla | M98: Indicação | N98: Hiring Manager | O98: 45760 | P98: 45763 | Q98: TRUE | R98: 5 | S98: TRUE | T98: 45765 | U98: TRUE | V98: 45770 | W98: TRUE | X98: 45779 | Y98: 69 | Z98: 74 | AA98: 78 | AB98: FALSE | AD98: FALSE | AF98: Test | AH98: 19 | AI98: Boa comunicação e resposta rápida.
A99: 95 | B99: Heloísa das Neves | C99: migueldas-neves@ig.com.br | D99: REQ-1006 | E99: People BP | F99: Operations | G99: Rio de Janeiro | H99: Remoto | I99: Pleno | J99: 3.7 | K99: Miguel | L99: Fernanda | M99: Evento | N99: Recruiter | O99: 45726 | P99: 45728 | Q99: FALSE | S99: FALSE | U99: FALSE | W99: FALSE | Y99: 64 | Z99: 61 | AA99: 65 | AB99: FALSE | AD99: FALSE | AF99: Rejected | AG99: No response | AH99: 2 | AI99: Boa comunicação e resposta rápida.
A100: 96 | B100: Danilo Pereira | C100: agatha73@da.org | D100: REQ-1076 | E100: Analista de Dados | F100: Data | G100: Campinas | H100: Remoto | I100: Senior | J100: 8.2 | K100: Felipe | L100: Diego | M100: LinkedIn | N100: Recruiter | O100: 45707 | P100: 45712 | Q100: TRUE | R100: 11 | S100: FALSE | U100: FALSE | W100: FALSE | Y100: 39 | Z100: 92 | AA100: 66 | AB100: FALSE | AD100: FALSE | AF100: Sourced | AG100: Failed technical test | AH100: 5 | AI100: Demonstrou interesse claro na oportunidade.
A101: 97 | B101: Sr. Pedro Henrique Melo | C101: carlos-eduardo02@da.net | D101: REQ-1071 | E101: Analista de Recrutamento | F101: Data | G101: São Paulo | H101: Presencial | I101: Pleno | J101: 5.9 | K101: Kamilly | L101: Fernanda | M101: Evento | N101: Tech Panel | O101: 45695 | P101: 45695 | Q101: TRUE | R101: 0 | S101: TRUE | T101: 45698 | U101: TRUE | V101: 45701 | W101: TRUE | X101: 45704 | Y101: 64 | Z101: 67 | AA101: 68 | AB101: FALSE | AD101: FALSE | AF101: Test | AG101: Timing mismatch | AH101: 9 | AI101: Bom potencial de evolução.
A102: 98 | B102: Breno da Cruz | C102: goncalvespedro-miguel@mendes.org | D102: REQ-1094 | E102: Talent Acquisition Specialist | F102: People | G102: São Paulo | H102: Híbrido | I102: Junior | J102: 3.4 | K102: Mirella | L102: Ana | M102: Evento | N102: Recruiter | O102: 45684 | P102: 45687 | Q102: TRUE | R102: 6 | S102: TRUE | T102: 45691 | U102: TRUE | V102: 45704 | W102: TRUE | X102: 45708 | Y102: 65 | Z102: 87 | AA102: 68 | AB102: FALSE | AD102: FALSE | AF102: Test | AG102: Headcount closed | AH102: 24 | AI102: Pediu prazo adicional para retorno.
...

Sheet tables
A1: Rótulos de Linha | B1: Contagem de candidate_id | D1: Contagem de candidate_id | E1: Rótulos de Coluna | I1: Contagem de candidate_id | J1: Rótulos de Coluna | N1: Rótulos de Linha | O1: Contagem de candidate_id
A2: Talent Acquisition Specialist | B2: 127 | D2: Rótulos de Linha | E2: FALSO | F2: VERDADEIRO | G2: Total Geral | I2: Rótulos de Linha | J2: FALSO | K2: VERDADEIRO | L2: Total Geral | N2: FALSO | O2: 552
A3: Analista de Recrutamento | B3: 147 | D3: Indicação | E3: 61 | F3: 3 | G3: 64 | I3: Ana | J3: 65 | K3: 10 | L3: 75 | N3: Culture add mismatch | O3: 12
A4: Analista de Dados | B4: 162 | D4: Evento | E4: 78 | F4: 4 | G4: 82 | I4: Bruno | J4: 83 | K4: 15 | L4: 98 | N4: Accepted another offer | O4: 18
A5: People BP | B5: 165 | D5: Banco de Talentos | E5: 62 | F5: 6 | G5: 68 | I5: Carla | J5: 92 | K5: 9 | L5: 101 | N5: Salary mismatch | O5: 18
A6: Total Geral | B6: 601 | D6: Hunting | E6: 68 | F6: 7 | G6: 75 | I6: Diego | J6: 98 | K6: 5 | L6: 103 | N6: Headcount closed | O6: 22
D7: Inbound | E7: 62 | F7: 7 | G7: 69 | I7: Fernanda | J7: 99 | K7: 4 | L7: 103 | N7: Low engagement | O7: 23
D8: LinkedIn | E8: 74 | F8: 7 | G8: 81 | I8: Gustavo | J8: 115 | K8: 6 | L8: 121 | N8: Low technical fit | O8: 23
D9: Comunidade | E9: 82 | F9: 7 | G9: 89 | I9: Total Geral | J9: 552 | K9: 49 | L9: 601 | N9: Timing mismatch | O9: 24
D10: Github | E10: 65 | F10: 8 | G10: 73 | K10: =GETPIVOTDATA("candidate_id",$I$1,"hired",TRUE)/GETPIVOTDATA("candidate_id",$I$1) -> 0.081530782 | N10: Failed technical test | O10: 25
D11: Total Geral | E11: 552 | F11: 49 | G11: 601 | N11: (vazio) | O11: 177
N12: No response | O12: 210
N13: VERDADEIRO | O13: 49
N14: (vazio) | O14: 49
N15: Total Geral | O15: 601
